{"v":"5.8.1","fr":29.9700012207031,"ip":0,"op":180.00000733155,"w":550,"h":550,"nm":"001-048 Bn","ddd":0,"assets":[{"id":"comp_0","nm":"Lupa 02 Bn","fr":30,"layers":[{"ddd":0,"ind":1,"ty":4,"nm":"Grupo 1 :M","sr":1,"ks":{"o":{"a":0,"k":100,"ix":11},"r":{"a":0,"k":0,"ix":10},"p":{"a":0,"k":[276.135,285.412,0],"ix":2,"l":2},"a":{"a":0,"k":[310.355,347.832,0],"ix":1,"l":2},"s":{"a":0,"k":[100,100,100],"ix":6,"l":2}},"ao":0,"shapes":[{"ty":"gr","it":[{"ty":"gr","it":[{"ind":0,"ty":"sh","ix":1,"ks":{"a":0,"k":{"i":[[-6.479,-16.414],[13.89,-1.511],[6.479,16.413],[-13.879,1.512]],"o":[[6.468,16.414],[-13.879,1.501],[-6.467,-16.414],[13.879,-1.5]],"v":[[25.137,-2.723],[11.713,29.729],[-25.138,2.723],[-11.725,-29.73]],"c":true},"ix":2},"nm":"Trazado 1","mn":"ADBE Vector Shape - Group","hd":false},{"ty":"st","c":{"a":0,"k":[0.5216,0,0,1],"ix":3},"o":{"a":0,"k":100,"ix":4},"w":{"a":0,"k":1.417,"ix":5},"lc":2,"lj":2,"bm":0,"nm":"Trazo 1","mn":"ADBE Vector Graphic - Stroke","hd":false},{"ty":"fl","c":{"a":0,"k":[1,1,1,1],"ix":4},"o":{"a":0,"k":50,"ix":5},"r":1,"bm":0,"nm":"Relleno 1","mn":"ADBE Vector Graphic - Fill","hd":false},{"ty":"tr","p":{"a":0,"k":[133.249,125.983],"ix":2},"a":{"a":0,"k":[0,0],"ix":1},"s":{"a":0,"k":[100,100],"ix":3},"r":{"a":0,"k":0,"ix":6},"o":{"a":0,"k":100,"ix":7},"sk":{"a":0,"k":0,"ix":4},"sa":{"a":0,"k":0,"ix":5},"nm":"Transformar"}],"nm":"Grupo 1","np":3,"cix":2,"bm":0,"ix":1,"mn":"ADBE Vector Group","hd":false},{"ty":"tr","p":{"a":0,"k":[268.456,287.449],"ix":2},"a":{"a":0,"k":[133.248,125.983],"ix":1},"s":{"a":0,"k":[257.386,257.386],"ix":3},"r":{"a":0,"k":0,"ix":6},"o":{"a":0,"k":100,"ix":7},"sk":{"a":0,"k":0,"ix":4},"sa":{"a":0,"k":0,"ix":5},"nm":"Transformar"}],"nm":"Grupo 1","np":1,"cix":2,"bm":0,"ix":1,"mn":"ADBE Vector Group","hd":false},{"ty":"gr","it":[{"ty":"gr","it":[{"ind":0,"ty":"sh","ix":1,"ks":{"a":0,"k":{"i":[[0,0],[0,0],[-0.466,0.489]],"o":[[0,0],[0.523,-0.432],[0,0]],"v":[[0.773,-0.603],[-0.773,0.693],[0.705,-0.694]],"c":true},"ix":2},"nm":"Trazado 1","mn":"ADBE Vector Shape - Group","hd":false},{"ty":"st","c":{"a":0,"k":[0.5216,0,0,1],"ix":3},"o":{"a":0,"k":100,"ix":4},"w":{"a":0,"k":2.835,"ix":5},"lc":2,"lj":2,"bm":0,"nm":"Trazo 1","mn":"ADBE Vector Graphic - Stroke","hd":false},{"ty":"fl","c":{"a":0,"k":[1,1,1,1],"ix":4},"o":{"a":0,"k":100,"ix":5},"r":1,"bm":0,"nm":"Relleno 1","mn":"ADBE Vector Graphic - Fill","hd":false},{"ty":"tr","p":{"a":0,"k":[159.205,155.918],"ix":2},"a":{"a":0,"k":[0,0],"ix":1},"s":{"a":0,"k":[100,100],"ix":3},"r":{"a":0,"k":0,"ix":6},"o":{"a":0,"k":100,"ix":7},"sk":{"a":0,"k":0,"ix":4},"sa":{"a":0,"k":0,"ix":5},"nm":"Transformar"}],"nm":"Grupo 2","np":3,"cix":2,"bm":0,"ix":1,"mn":"ADBE Vector Group","hd":false},{"ty":"tr","p":{"a":0,"k":[335.263,364.497],"ix":2},"a":{"a":0,"k":[159.205,155.918],"ix":1},"s":{"a":0,"k":[257.386,257.386],"ix":3},"r":{"a":0,"k":0,"ix":6},"o":{"a":0,"k":100,"ix":7},"sk":{"a":0,"k":0,"ix":4},"sa":{"a":0,"k":0,"ix":5},"nm":"Transformar"}],"nm":"Grupo 2","np":1,"cix":2,"bm":0,"ix":2,"mn":"ADBE Vector Group","hd":false},{"ty":"gr","it":[{"ty":"gr","it":[{"ind":0,"ty":"sh","ix":1,"ks":{"a":0,"k":{"i":[[-13.879,1.5],[6.468,16.413],[13.879,-1.5],[-6.468,-16.413]],"o":[[13.89,-1.512],[-6.479,-16.414],[-13.878,1.512],[6.479,16.414]],"v":[[11.896,29.736],[25.319,-2.716],[-11.544,-29.724],[-24.956,2.728]],"c":true},"ix":2},"nm":"Trazado 1","mn":"ADBE Vector Shape - Group","hd":false},{"ind":1,"ty":"sh","ix":2,"ks":{"a":0,"k":{"i":[[-7.684,-19.483],[6.744,-7.032],[0.523,-0.432],[0,0],[1.478,-0.705],[2.648,-0.285],[7.673,19.471],[-7.991,6.718],[-4.478,0.489]],"o":[[5.229,13.254],[-0.467,0.488],[0,0],[-1.216,1.023],[-2.148,1.034],[-16.471,1.784],[-5.592,-14.175],[2.989,-2.512],[16.471,-1.785]],"v":[[30.003,-3.228],[26.842,29.247],[25.366,30.634],[25.343,30.657],[21.296,33.26],[14.089,35.272],[-29.64,3.24],[-24.99,-30.645],[-13.726,-35.271]],"c":true},"ix":2},"nm":"Trazado 2","mn":"ADBE Vector Shape - Group","hd":false},{"ty":"mm","mm":1,"nm":"Combinar trazados 1","mn":"ADBE Vector Filter - Merge","hd":false},{"ty":"st","c":{"a":0,"k":[0.5216,0,0,1],"ix":3},"o":{"a":0,"k":100,"ix":4},"w":{"a":0,"k":2.835,"ix":5},"lc":2,"lj":2,"bm":0,"nm":"Trazo 1","mn":"ADBE Vector Graphic - Stroke","hd":false},{"ty":"fl","c":{"a":0,"k":[0.8,0.8,0.8,1],"ix":4},"o":{"a":0,"k":100,"ix":5},"r":1,"bm":0,"nm":"Relleno 1","mn":"ADBE Vector Graphic - Fill","hd":false},{"ty":"tr","p":{"a":0,"k":[133.067,125.977],"ix":2},"a":{"a":0,"k":[0,0],"ix":1},"s":{"a":0,"k":[100,100],"ix":3},"r":{"a":0,"k":0,"ix":6},"o":{"a":0,"k":100,"ix":7},"sk":{"a":0,"k":0,"ix":4},"sa":{"a":0,"k":0,"ix":5},"nm":"Transformar"}],"nm":"Grupo 3","np":5,"cix":2,"bm":0,"ix":1,"mn":"ADBE Vector Group","hd":false},{"ty":"tr","p":{"a":0,"k":[268.45,287.435],"ix":2},"a":{"a":0,"k":[133.246,125.977],"ix":1},"s":{"a":0,"k":[257.386,257.386],"ix":3},"r":{"a":0,"k":0,"ix":6},"o":{"a":0,"k":100,"ix":7},"sk":{"a":0,"k":0,"ix":4},"sa":{"a":0,"k":0,"ix":5},"nm":"Transformar"}],"nm":"Grupo 3","np":1,"cix":2,"bm":0,"ix":3,"mn":"ADBE Vector Group","hd":false},{"ty":"gr","it":[{"ty":"gr","it":[{"ind":0,"ty":"sh","ix":1,"ks":{"a":0,"k":{"i":[[0,0],[0.694,1.046],[0,0],[-1.216,1.023],[0,0]],"o":[[0.637,0.978],[0,0],[1.477,-0.705],[0,0],[0,0]],"v":[[5.143,1.551],[-0.518,5.393],[-5.78,-2.517],[-1.734,-5.121],[-0.165,-6.439]],"c":true},"ix":2},"nm":"Trazado 1","mn":"ADBE Vector Shape - Group","hd":false},{"ty":"st","c":{"a":0,"k":[0.5216,0,0,1],"ix":3},"o":{"a":0,"k":100,"ix":4},"w":{"a":0,"k":2.835,"ix":5},"lc":2,"lj":2,"bm":0,"nm":"Trazo 1","mn":"ADBE Vector Graphic - Stroke","hd":false},{"ty":"fl","c":{"a":0,"k":[0.5216,0,0,1],"ix":4},"o":{"a":0,"k":100,"ix":5},"r":1,"bm":0,"nm":"Relleno 1","mn":"ADBE Vector Graphic - Fill","hd":false},{"ty":"tr","p":{"a":0,"k":[160.143,161.754],"ix":2},"a":{"a":0,"k":[0,0],"ix":1},"s":{"a":0,"k":[100,100],"ix":3},"r":{"a":0,"k":0,"ix":6},"o":{"a":0,"k":100,"ix":7},"sk":{"a":0,"k":0,"ix":4},"sa":{"a":0,"k":0,"ix":5},"nm":"Transformar"}],"nm":"Grupo 4","np":3,"cix":2,"bm":0,"ix":1,"mn":"ADBE Vector Group","hd":false},{"ty":"tr","p":{"a":0,"k":[336.924,378.401],"ix":2},"a":{"a":0,"k":[159.85,161.32],"ix":1},"s":{"a":0,"k":[257.386,257.386],"ix":3},"r":{"a":0,"k":0,"ix":6},"o":{"a":0,"k":100,"ix":7},"sk":{"a":0,"k":0,"ix":4},"sa":{"a":0,"k":0,"ix":5},"nm":"Transformar"}],"nm":"Grupo 4","np":1,"cix":2,"bm":0,"ix":4,"mn":"ADBE Vector Group","hd":false},{"ty":"gr","it":[{"ty":"gr","it":[{"ind":0,"ty":"sh","ix":1,"ks":{"a":0,"k":{"i":[[-0.762,-0.989],[1.625,2.512],[-2.501,2.137],[0,0],[0.636,0.978],[0,0]],"o":[[2.262,3.251],[-0.773,-1],[0,0],[0.694,1.046],[0,0],[2.421,-1.25]],"v":[[6.479,-5.768],[-7.968,4.246],[-4.524,-1.096],[-4.081,-0.437],[1.58,-4.279],[1.137,-4.95]],"c":true},"ix":2},"nm":"Trazado 1","mn":"ADBE Vector Shape - Group","hd":false},{"ty":"st","c":{"a":0,"k":[0.5216,0,0,1],"ix":3},"o":{"a":0,"k":100,"ix":4},"w":{"a":0,"k":2.835,"ix":5},"lc":2,"lj":2,"bm":0,"nm":"Trazo 1","mn":"ADBE Vector Graphic - Stroke","hd":false},{"ty":"fl","c":{"a":0,"k":[0.616,0.584,0.584,1],"ix":4},"o":{"a":0,"k":100,"ix":5},"r":1,"bm":0,"nm":"Relleno 1","mn":"ADBE Vector Graphic - Fill","hd":false},{"ty":"tr","p":{"a":0,"k":[163.706,167.585],"ix":2},"a":{"a":0,"k":[0,0],"ix":1},"s":{"a":0,"k":[100,100],"ix":3},"r":{"a":0,"k":0,"ix":6},"o":{"a":0,"k":100,"ix":7},"sk":{"a":0,"k":0,"ix":4},"sa":{"a":0,"k":0,"ix":5},"nm":"Transformar"}],"nm":"Grupo 5","np":3,"cix":2,"bm":0,"ix":1,"mn":"ADBE Vector Group","hd":false},{"ty":"tr","p":{"a":0,"k":[344.99,392.464],"ix":2},"a":{"a":0,"k":[162.984,166.783],"ix":1},"s":{"a":0,"k":[257.386,257.386],"ix":3},"r":{"a":0,"k":0,"ix":6},"o":{"a":0,"k":100,"ix":7},"sk":{"a":0,"k":0,"ix":4},"sa":{"a":0,"k":0,"ix":5},"nm":"Transformar"}],"nm":"Grupo 5","np":1,"cix":2,"bm":0,"ix":5,"mn":"ADBE Vector Group","hd":false},{"ty":"gr","it":[{"ty":"gr","it":[{"ind":0,"ty":"sh","ix":1,"ks":{"a":0,"k":{"i":[[-7.673,-19.483],[8.002,-6.706],[0,0],[0,0],[5.229,13.254],[16.47,-1.785],[2.99,-2.512],[0,0],[-4.479,0.489]],"o":[[5.593,14.175],[0,0],[0,0],[6.763,-7.013],[-7.684,-19.483],[-4.479,0.489],[0,0],[2.978,-2.512],[16.47,-1.785]],"v":[[28.928,-2.915],[24.269,30.957],[17.379,36.744],[17.311,36.653],[20.471,4.178],[-23.257,-27.865],[-34.521,-23.24],[-26.053,-30.332],[-14.8,-34.959]],"c":true},"ix":2},"nm":"Trazado 1","mn":"ADBE Vector Shape - Group","hd":false},{"ty":"st","c":{"a":0,"k":[0.5216,0,0,1],"ix":3},"o":{"a":0,"k":100,"ix":4},"w":{"a":0,"k":2.835,"ix":5},"lc":2,"lj":2,"bm":0,"nm":"Trazo 1","mn":"ADBE Vector Graphic - Stroke","hd":false},{"ty":"fl","c":{"a":0,"k":[1,0.8588,0.8588,1],"ix":4},"o":{"a":0,"k":100,"ix":5},"r":1,"bm":0,"nm":"Relleno 1","mn":"ADBE Vector Graphic - Fill","hd":false},{"ty":"tr","p":{"a":0,"k":[142.598,118.571],"ix":2},"a":{"a":0,"k":[0,0],"ix":1},"s":{"a":0,"k":[100,100],"ix":3},"r":{"a":0,"k":0,"ix":6},"o":{"a":0,"k":100,"ix":7},"sk":{"a":0,"k":0,"ix":4},"sa":{"a":0,"k":0,"ix":5},"nm":"Transformar"}],"nm":"Grupo 6","np":3,"cix":2,"bm":0,"ix":1,"mn":"ADBE Vector Group","hd":false},{"ty":"tr","p":{"a":0,"k":[289.303,270.478],"ix":2},"a":{"a":0,"k":[141.348,119.389],"ix":1},"s":{"a":0,"k":[257.386,257.386],"ix":3},"r":{"a":0,"k":0,"ix":6},"o":{"a":0,"k":100,"ix":7},"sk":{"a":0,"k":0,"ix":4},"sa":{"a":0,"k":0,"ix":5},"nm":"Transformar"}],"nm":"Grupo 6","np":1,"cix":2,"bm":0,"ix":6,"mn":"ADBE Vector Group","hd":false},{"ty":"gr","it":[{"ty":"gr","it":[{"ind":0,"ty":"sh","ix":1,"ks":{"a":0,"k":{"i":[[0,0],[4.433,-3.058],[1.864,0],[1.853,2.864],[0,0],[2.262,3.251]],"o":[[3.092,4.433],[-1.659,1.137],[-3.149,0],[0,0],[1.626,2.512],[0,0]],"v":[[19.068,11.492],[16.624,25.121],[11.214,26.803],[3.132,22.393],[-22.16,-16.789],[-7.712,-26.803]],"c":true},"ix":2},"nm":"Trazado 1","mn":"ADBE Vector Shape - Group","hd":false},{"ty":"st","c":{"a":0,"k":[0.5216,0,0,1],"ix":3},"o":{"a":0,"k":100,"ix":4},"w":{"a":0,"k":2.835,"ix":5},"lc":2,"lj":2,"bm":0,"nm":"Trazo 1","mn":"ADBE Vector Graphic - Stroke","hd":false},{"ty":"fl","c":{"a":0,"k":[0.616,0.584,0.584,1],"ix":4},"o":{"a":0,"k":100,"ix":5},"r":1,"bm":0,"nm":"Relleno 1","mn":"ADBE Vector Graphic - Fill","hd":false},{"ty":"tr","p":{"a":0,"k":[177.897,188.62],"ix":2},"a":{"a":0,"k":[0,0],"ix":1},"s":{"a":0,"k":[100,100],"ix":3},"r":{"a":0,"k":0,"ix":6},"o":{"a":0,"k":100,"ix":7},"sk":{"a":0,"k":0,"ix":4},"sa":{"a":0,"k":0,"ix":5},"nm":"Transformar"}],"nm":"Grupo 7","np":3,"cix":2,"bm":0,"ix":1,"mn":"ADBE Vector Group","hd":false},{"ty":"tr","p":{"a":0,"k":[381.655,448.668],"ix":2},"a":{"a":0,"k":[177.229,188.62],"ix":1},"s":{"a":0,"k":[257.386,257.386],"ix":3},"r":{"a":0,"k":0,"ix":6},"o":{"a":0,"k":100,"ix":7},"sk":{"a":0,"k":0,"ix":4},"sa":{"a":0,"k":0,"ix":5},"nm":"Transformar"}],"nm":"Grupo 7","np":1,"cix":2,"bm":0,"ix":7,"mn":"ADBE Vector Group","hd":false},{"ty":"gr","it":[{"ty":"gr","it":[{"ind":0,"ty":"sh","ix":1,"ks":{"a":0,"k":{"i":[[-16.462,-12.179],[-8.36,5.861],[0,0],[0,0],[11.196,8.294],[-5.855,15.106],[-3.13,2.188],[0,0],[1.595,-4.107]],"o":[[11.974,8.871],[0,0],[0,0],[-8.336,4.613],[-16.459,-12.19],[1.596,-4.107],[0,0],[-3.127,2.177],[-5.855,15.106]],"v":[[-7.665,27.522],[25.51,31.695],[32.72,26.652],[32.651,26.564],[1.176,21.33],[-18.025,-28.086],[-10.804,-37.556],[-19.647,-31.351],[-26.865,-21.893]],"c":true},"ix":2},"nm":"Trazado 1","mn":"ADBE Vector Shape - Group","hd":false},{"ty":"st","c":{"a":0,"k":[0.5216,0,0,1],"ix":3},"o":{"a":0,"k":100,"ix":4},"w":{"a":0,"k":2.835,"ix":5},"lc":2,"lj":2,"bm":0,"nm":"Trazo 1","mn":"ADBE Vector Graphic - Stroke","hd":false},{"ty":"fl","c":{"a":0,"k":[1,0.8588,0.8588,1],"ix":4},"o":{"a":0,"k":100,"ix":5},"r":1,"bm":0,"nm":"Relleno 1","mn":"ADBE Vector Graphic - Fill","hd":false},{"ty":"tr","p":{"a":0,"k":[133.131,123.777],"ix":2},"a":{"a":0,"k":[0,0],"ix":1},"s":{"a":0,"k":[100,100],"ix":3},"r":{"a":0,"k":0,"ix":6},"o":{"a":0,"k":100,"ix":7},"sk":{"a":0,"k":0,"ix":4},"sa":{"a":0,"k":0,"ix":5},"nm":"Transformar"}],"nm":"Grupo 18","np":3,"cix":2,"bm":0,"ix":1,"mn":"ADBE Vector Group","hd":false},{"ty":"tr","p":{"a":0,"k":[273.322,278.888],"ix":2},"a":{"a":0,"k":[135.139,122.656],"ix":1},"s":{"a":0,"k":[257.386,257.386],"ix":3},"r":{"a":0,"k":0,"ix":6},"o":{"a":0,"k":100,"ix":7},"sk":{"a":0,"k":0,"ix":4},"sa":{"a":0,"k":0,"ix":5},"nm":"Transformar"}],"nm":"Grupo 118","np":1,"cix":2,"bm":0,"ix":8,"mn":"ADBE Vector Group","hd":false}],"ip":0,"op":180.00000733155,"st":0,"bm":0}]}],"layers":[{"ddd":0,"ind":1,"ty":0,"nm":"Lupa 02 Bn","refId":"comp_0","sr":1,"ks":{"o":{"a":0,"k":100,"ix":11},"r":{"a":0,"k":122.894,"ix":10},"p":{"a":1,"k":[{"i":{"x":0.53,"y":1},"o":{"x":0.47,"y":0},"t":0,"s":[235,167,0],"to":[0,0,0],"ti":[0,0,0]},{"i":{"x":0.53,"y":1},"o":{"x":0.47,"y":0},"t":60,"s":[235,357,0],"to":[0,0,0],"ti":[0,0,0]},{"i":{"x":0.53,"y":1},"o":{"x":0.47,"y":0},"t":120,"s":[341,223,0],"to":[0,0,0],"ti":[0,0,0]},{"t":179.000007290819,"s":[235,167,0]}],"ix":2,"l":2},"a":{"a":0,"k":[275,275,0],"ix":1,"l":2},"s":{"a":0,"k":[93.207,93.207,100],"ix":6,"l":2}},"ao":0,"w":550,"h":550,"ip":0,"op":179.820007324219,"st":0,"bm":0},{"ddd":0,"ind":2,"ty":4,"nm":"48 contornos","sr":1,"ks":{"o":{"a":0,"k":100,"ix":11},"r":{"a":0,"k":0,"ix":10},"p":{"a":0,"k":[275,331,0],"ix":2,"l":2},"a":{"a":0,"k":[115.5,75,0],"ix":1,"l":2},"s":{"a":0,"k":[214.667,214.667,100],"ix":6,"l":2}},"ao":0,"shapes":[{"ty":"gr","it":[{"ind":0,"ty":"sh","ix":1,"ks":{"a":0,"k":{"i":[[-0.054,4.87],[0.001,-0.238],[-0.087,-1.334],[8.546,-1.073],[1.193,6.117],[0,2.516],[0,0],[0,0],[-0.509,-2.614],[-10.411,1.313]],"o":[[0,0],[-0.006,1.183],[0.325,5.053],[-10.411,1.313],[-0.52,-2.614],[0,0],[0,0],[0,2.505],[1.193,6.117],[8.286,-1.041]],"v":[[18.188,-10.607],[18.069,1.42],[18.177,5.206],[4.013,15.801],[-17.743,6.843],[-18.502,-0.846],[-18.502,-17.114],[-18.491,-17.114],[-17.743,-9.425],[4.013,-0.467]],"c":true},"ix":2},"nm":"Trazado 1","mn":"ADBE Vector Shape - Group","hd":false},{"ty":"st","c":{"a":0,"k":[0.5216,0,0,1],"ix":3},"o":{"a":0,"k":100,"ix":4},"w":{"a":0,"k":2.835,"ix":5},"lc":2,"lj":2,"bm":0,"nm":"Trazo 1","mn":"ADBE Vector Graphic - Stroke","hd":false},{"ty":"fl","c":{"a":0,"k":[0.424,0.376,0.376,1],"ix":4},"o":{"a":0,"k":100,"ix":5},"r":1,"bm":0,"nm":"Relleno 1","mn":"ADBE Vector Graphic - Fill","hd":false},{"ty":"tr","p":{"a":0,"k":[90.471,94.38],"ix":2},"a":{"a":0,"k":[0,0],"ix":1},"s":{"a":0,"k":[100,100],"ix":3},"r":{"a":0,"k":0,"ix":6},"o":{"a":0,"k":100,"ix":7},"sk":{"a":0,"k":0,"ix":4},"sa":{"a":0,"k":0,"ix":5},"nm":"Transformar"}],"nm":"Grupo 1","np":3,"cix":2,"bm":0,"ix":1,"mn":"ADBE Vector Group","hd":false},{"ty":"gr","it":[{"ind":0,"ty":"sh","ix":1,"ks":{"a":0,"k":{"i":[[-2.549,-0.108],[0,-1.974],[0.021,-0.152],[2.56,0.108],[0,1.963],[0,0],[-0.02,0.152]],"o":[[2.386,0.108],[0,0.152],[-0.302,2.179],[-2.364,-0.109],[0,0],[0,-0.152],[0.297,-2.178]],"v":[[0.52,-3.943],[4.652,-0.245],[4.62,0.201],[-0.532,3.943],[-4.653,0.254],[-4.653,0.243],[-4.621,-0.201]],"c":true},"ix":2},"nm":"Trazado 1","mn":"ADBE Vector Shape - Group","hd":false},{"ty":"st","c":{"a":0,"k":[0.5216,0,0,1],"ix":3},"o":{"a":0,"k":100,"ix":4},"w":{"a":0,"k":2.835,"ix":5},"lc":2,"lj":2,"bm":0,"nm":"Trazo 1","mn":"ADBE Vector Graphic - Stroke","hd":false},{"ty":"fl","c":{"a":0,"k":[1,0.8588,0.8588,1],"ix":4},"o":{"a":0,"k":100,"ix":5},"r":1,"bm":0,"nm":"Relleno 1","mn":"ADBE Vector Graphic - Fill","hd":false},{"ty":"tr","p":{"a":0,"k":[110.22,18.252],"ix":2},"a":{"a":0,"k":[0,0],"ix":1},"s":{"a":0,"k":[100,100],"ix":3},"r":{"a":0,"k":0,"ix":6},"o":{"a":0,"k":100,"ix":7},"sk":{"a":0,"k":0,"ix":4},"sa":{"a":0,"k":0,"ix":5},"nm":"Transformar"}],"nm":"Grupo 2","np":3,"cix":2,"bm":0,"ix":2,"mn":"ADBE Vector Group","hd":false},{"ty":"gr","it":[{"ind":0,"ty":"sh","ix":1,"ks":{"a":0,"k":{"i":[[0,0.152],[0,0],[2.971,-1.214],[0,0],[-2.364,-0.108],[-0.302,2.178]],"o":[[0,0],[-3.232,0.672],[0,0],[0,1.963],[2.559,0.109],[0.021,-0.152]],"v":[[4.652,-5.352],[4.652,2.533],[-4.653,5.352],[-4.653,-4.853],[-0.532,-1.166],[4.62,-4.907]],"c":true},"ix":2},"nm":"Trazado 1","mn":"ADBE Vector Shape - Group","hd":false},{"ty":"st","c":{"a":0,"k":[0.5216,0,0,1],"ix":3},"o":{"a":0,"k":100,"ix":4},"w":{"a":0,"k":2.835,"ix":5},"lc":2,"lj":2,"bm":0,"nm":"Trazo 1","mn":"ADBE Vector Graphic - Stroke","hd":false},{"ty":"fl","c":{"a":0,"k":[0.424,0.376,0.376,1],"ix":4},"o":{"a":0,"k":100,"ix":5},"r":1,"bm":0,"nm":"Relleno 1","mn":"ADBE Vector Graphic - Fill","hd":false},{"ty":"tr","p":{"a":0,"k":[110.22,23.359],"ix":2},"a":{"a":0,"k":[0,0],"ix":1},"s":{"a":0,"k":[100,100],"ix":3},"r":{"a":0,"k":0,"ix":6},"o":{"a":0,"k":100,"ix":7},"sk":{"a":0,"k":0,"ix":4},"sa":{"a":0,"k":0,"ix":5},"nm":"Transformar"}],"nm":"Grupo 3","np":3,"cix":2,"bm":0,"ix":3,"mn":"ADBE Vector Group","hd":false},{"ty":"gr","it":[{"ind":0,"ty":"sh","ix":1,"ks":{"a":0,"k":{"i":[[-0.043,0.011],[0,0],[0.043,0]],"o":[[0,0],[-0.043,0],[0.043,-0.011]],"v":[[0.065,-0.011],[0.065,0],[-0.065,0.011]],"c":true},"ix":2},"nm":"Trazado 1","mn":"ADBE Vector Shape - Group","hd":false},{"ty":"st","c":{"a":0,"k":[0.5216,0,0,1],"ix":3},"o":{"a":0,"k":100,"ix":4},"w":{"a":0,"k":2.835,"ix":5},"lc":2,"lj":2,"bm":0,"nm":"Trazo 1","mn":"ADBE Vector Graphic - Stroke","hd":false},{"ty":"fl","c":{"a":0,"k":[1,1,1,1],"ix":4},"o":{"a":0,"k":100,"ix":5},"r":1,"bm":0,"nm":"Relleno 1","mn":"ADBE Vector Graphic - Fill","hd":false},{"ty":"tr","p":{"a":0,"k":[119.905,25.057],"ix":2},"a":{"a":0,"k":[0,0],"ix":1},"s":{"a":0,"k":[100,100],"ix":3},"r":{"a":0,"k":0,"ix":6},"o":{"a":0,"k":100,"ix":7},"sk":{"a":0,"k":0,"ix":4},"sa":{"a":0,"k":0,"ix":5},"nm":"Transformar"}],"nm":"Grupo 4","np":3,"cix":2,"bm":0,"ix":4,"mn":"ADBE Vector Group","hd":false},{"ty":"gr","it":[{"ind":0,"ty":"sh","ix":1,"ks":{"a":0,"k":{"i":[[-0.022,0.304],[0,0],[3.731,-0.597],[0,0],[-2.44,-0.25],[-0.852,2.561]],"o":[[0,0],[-3.753,-0.173],[0,0],[0.098,1.952],[3.015,0.325],[0.105,-0.316]],"v":[[5.656,-4.642],[5.656,4.023],[-5.656,4.642],[-5.656,-3.416],[-1.491,0.369],[5.461,-3.698]],"c":true},"ix":2},"nm":"Trazado 1","mn":"ADBE Vector Shape - Group","hd":false},{"ty":"st","c":{"a":0,"k":[0.5216,0,0,1],"ix":3},"o":{"a":0,"k":100,"ix":4},"w":{"a":0,"k":2.835,"ix":5},"lc":2,"lj":2,"bm":0,"nm":"Trazo 1","mn":"ADBE Vector Graphic - Stroke","hd":false},{"ty":"fl","c":{"a":0,"k":[0.424,0.376,0.376,1],"ix":4},"o":{"a":0,"k":100,"ix":5},"r":1,"bm":0,"nm":"Relleno 1","mn":"ADBE Vector Graphic - Fill","hd":false},{"ty":"tr","p":{"a":0,"k":[125.626,20.404],"ix":2},"a":{"a":0,"k":[0,0],"ix":1},"s":{"a":0,"k":[100,100],"ix":3},"r":{"a":0,"k":0,"ix":6},"o":{"a":0,"k":100,"ix":7},"sk":{"a":0,"k":0,"ix":4},"sa":{"a":0,"k":0,"ix":5},"nm":"Transformar"}],"nm":"Grupo 5","np":3,"cix":2,"bm":0,"ix":5,"mn":"ADBE Vector Group","hd":false},{"ty":"gr","it":[{"ind":0,"ty":"sh","ix":1,"ks":{"a":0,"k":{"i":[[-3.753,-0.173],[0,0],[3.633,-0.456],[0,0]],"o":[[0,0],[-3.904,-0.087],[0,0],[3.731,-0.596]],"v":[[5.656,-0.228],[5.656,-0.13],[-5.656,0.401],[-5.656,0.39]],"c":true},"ix":2},"nm":"Trazado 1","mn":"ADBE Vector Shape - Group","hd":false},{"ty":"st","c":{"a":0,"k":[0.5216,0,0,1],"ix":3},"o":{"a":0,"k":100,"ix":4},"w":{"a":0,"k":2.835,"ix":5},"lc":2,"lj":2,"bm":0,"nm":"Trazo 1","mn":"ADBE Vector Graphic - Stroke","hd":false},{"ty":"fl","c":{"a":0,"k":[1,1,1,1],"ix":4},"o":{"a":0,"k":100,"ix":5},"r":1,"bm":0,"nm":"Relleno 1","mn":"ADBE Vector Graphic - Fill","hd":false},{"ty":"tr","p":{"a":0,"k":[125.626,24.656],"ix":2},"a":{"a":0,"k":[0,0],"ix":1},"s":{"a":0,"k":[100,100],"ix":3},"r":{"a":0,"k":0,"ix":6},"o":{"a":0,"k":100,"ix":7},"sk":{"a":0,"k":0,"ix":4},"sa":{"a":0,"k":0,"ix":5},"nm":"Transformar"}],"nm":"Grupo 6","np":3,"cix":2,"bm":0,"ix":6,"mn":"ADBE Vector Group","hd":false},{"ty":"gr","it":[{"ind":0,"ty":"sh","ix":1,"ks":{"a":0,"k":{"i":[[0.165,-2.181],[0.105,-0.316],[3.015,0.325],[0.094,1.952],[-0.161,0.499],[-3.015,-0.314]],"o":[[-0.023,0.304],[-0.852,2.561],[-2.44,-0.25],[-0.022,-0.467],[0.831,-2.568],[2.636,0.282]],"v":[[5.585,-0.363],[5.39,0.58],[-1.562,4.647],[-5.727,0.863],[-5.532,-0.581],[1.42,-4.659]],"c":true},"ix":2},"nm":"Trazado 1","mn":"ADBE Vector Shape - Group","hd":false},{"ty":"st","c":{"a":0,"k":[0.5216,0,0,1],"ix":3},"o":{"a":0,"k":100,"ix":4},"w":{"a":0,"k":2.835,"ix":5},"lc":2,"lj":2,"bm":0,"nm":"Trazo 1","mn":"ADBE Vector Graphic - Stroke","hd":false},{"ty":"fl","c":{"a":0,"k":[1,0.8588,0.8588,1],"ix":4},"o":{"a":0,"k":100,"ix":5},"r":1,"bm":0,"nm":"Relleno 1","mn":"ADBE Vector Graphic - Fill","hd":false},{"ty":"tr","p":{"a":0,"k":[125.698,16.126],"ix":2},"a":{"a":0,"k":[0,0],"ix":1},"s":{"a":0,"k":[100,100],"ix":3},"r":{"a":0,"k":0,"ix":6},"o":{"a":0,"k":100,"ix":7},"sk":{"a":0,"k":0,"ix":4},"sa":{"a":0,"k":0,"ix":5},"nm":"Transformar"}],"nm":"Grupo 7","np":3,"cix":2,"bm":0,"ix":7,"mn":"ADBE Vector Group","hd":false},{"ty":"gr","it":[{"ind":0,"ty":"sh","ix":1,"ks":{"a":0,"k":{"i":[[0,0],[-0.955,-0.087],[0.954,0.021]],"o":[[0.965,0.043],[-0.976,-0.054],[0,0]],"v":[[-1.443,-0.103],[1.443,0.103],[-1.443,-0.005]],"c":true},"ix":2},"nm":"Trazado 1","mn":"ADBE Vector Shape - Group","hd":false},{"ty":"st","c":{"a":0,"k":[0.5216,0,0,1],"ix":3},"o":{"a":0,"k":100,"ix":4},"w":{"a":0,"k":2.835,"ix":5},"lc":2,"lj":2,"bm":0,"nm":"Trazo 1","mn":"ADBE Vector Graphic - Stroke","hd":false},{"ty":"fl","c":{"a":0,"k":[1,1,1,1],"ix":4},"o":{"a":0,"k":100,"ix":5},"r":1,"bm":0,"nm":"Relleno 1","mn":"ADBE Vector Graphic - Fill","hd":false},{"ty":"tr","p":{"a":0,"k":[132.725,24.531],"ix":2},"a":{"a":0,"k":[0,0],"ix":1},"s":{"a":0,"k":[100,100],"ix":3},"r":{"a":0,"k":0,"ix":6},"o":{"a":0,"k":100,"ix":7},"sk":{"a":0,"k":0,"ix":4},"sa":{"a":0,"k":0,"ix":5},"nm":"Transformar"}],"nm":"Grupo 8","np":3,"cix":2,"bm":0,"ix":8,"mn":"ADBE Vector Group","hd":false},{"ty":"gr","it":[{"ind":0,"ty":"sh","ix":1,"ks":{"a":0,"k":{"i":[[0,-1.562],[0.868,-1.052],[3.2,0.878],[0,1.562],[-0.868,1.052],[-3.21,-0.879]],"o":[[0,0.987],[-2.256,2.733],[-1.974,-0.543],[0,-0.976],[2.256,-2.733],[1.974,0.542]],"v":[[7.087,-1.534],[5.808,1.59],[-4.073,4.952],[-7.087,1.535],[-5.807,-1.589],[4.073,-4.95]],"c":true},"ix":2},"nm":"Trazado 1","mn":"ADBE Vector Shape - Group","hd":false},{"ty":"st","c":{"a":0,"k":[0.5216,0,0,1],"ix":3},"o":{"a":0,"k":100,"ix":4},"w":{"a":0,"k":2.835,"ix":5},"lc":2,"lj":2,"bm":0,"nm":"Trazo 1","mn":"ADBE Vector Graphic - Stroke","hd":false},{"ty":"fl","c":{"a":0,"k":[1,0.8588,0.8588,1],"ix":4},"o":{"a":0,"k":100,"ix":5},"r":1,"bm":0,"nm":"Relleno 1","mn":"ADBE Vector Graphic - Fill","hd":false},{"ty":"tr","p":{"a":0,"k":[142.859,16.169],"ix":2},"a":{"a":0,"k":[0,0],"ix":1},"s":{"a":0,"k":[100,100],"ix":3},"r":{"a":0,"k":0,"ix":6},"o":{"a":0,"k":100,"ix":7},"sk":{"a":0,"k":0,"ix":4},"sa":{"a":0,"k":0,"ix":5},"nm":"Transformar"}],"nm":"Grupo 9","np":3,"cix":2,"bm":0,"ix":9,"mn":"ADBE Vector Group","hd":false},{"ty":"gr","it":[{"ind":0,"ty":"sh","ix":1,"ks":{"a":0,"k":{"i":[[0,0.987],[0,0],[5.163,0.64],[0,0],[-1.974,-0.543],[-2.256,2.733]],"o":[[0,0],[-4.121,-1.898],[0,0],[0,1.562],[3.2,0.878],[0.868,-1.052]],"v":[[7.087,-7.012],[7.087,7.012],[-7.087,3.161],[-7.087,-3.942],[-4.073,-0.526],[5.808,-3.887]],"c":true},"ix":2},"nm":"Trazado 1","mn":"ADBE Vector Shape - Group","hd":false},{"ty":"st","c":{"a":0,"k":[0.5216,0,0,1],"ix":3},"o":{"a":0,"k":100,"ix":4},"w":{"a":0,"k":2.835,"ix":5},"lc":2,"lj":2,"bm":0,"nm":"Trazo 1","mn":"ADBE Vector Graphic - Stroke","hd":false},{"ty":"fl","c":{"a":0,"k":[0.424,0.376,0.376,1],"ix":4},"o":{"a":0,"k":100,"ix":5},"r":1,"bm":0,"nm":"Relleno 1","mn":"ADBE Vector Graphic - Fill","hd":false},{"ty":"tr","p":{"a":0,"k":[142.859,21.646],"ix":2},"a":{"a":0,"k":[0,0],"ix":1},"s":{"a":0,"k":[100,100],"ix":3},"r":{"a":0,"k":0,"ix":6},"o":{"a":0,"k":100,"ix":7},"sk":{"a":0,"k":0,"ix":4},"sa":{"a":0,"k":0,"ix":5},"nm":"Transformar"}],"nm":"Grupo 10","np":3,"cix":2,"bm":0,"ix":10,"mn":"ADBE Vector Group","hd":false},{"ty":"gr","it":[{"ind":0,"ty":"sh","ix":1,"ks":{"a":0,"k":{"i":[[-0.376,-1.899],[0,-0.607],[12.548,-3.134],[-1.974,-29.026],[0.001,-0.152],[8.286,-1.041],[1.193,6.117],[0,2.506],[-7.689,9.88],[-7.7,3.134],[-3.232,0.672],[-1.681,0.217],[-0.044,0],[-3.904,-0.087],[-0.976,-0.054],[0,0],[-0.531,-0.065],[-4.118,-1.905],[-0.562,-0.295],[-1.779,-2.169]],"o":[[0.12,0.607],[0,6.171],[-14.165,3.536],[0.01,0.152],[-0.027,4.869],[-10.412,1.312],[-0.51,-2.614],[0,-12.146],[5.77,-7.408],[2.972,-1.215],[1.627,-0.336],[0.043,0],[3.633,-0.456],[0.955,0.022],[0,0],[0.531,0.054],[5.163,0.636],[0.608,0.281],[2.968,1.559],[1.561,1.909]],"v":[[44.823,-18.941],[45.008,-17.119],[26.072,-2.207],[-8.34,23.486],[-8.33,23.942],[-22.505,34.082],[-44.26,25.124],[-45.009,17.434],[-31.691,-15.535],[-11.421,-31.12],[-2.116,-33.94],[2.852,-34.764],[2.983,-34.775],[14.293,-35.307],[17.179,-35.198],[17.19,-35.198],[18.783,-35.025],[32.958,-31.174],[34.716,-30.307],[41.918,-24.678]],"c":true},"ix":2},"nm":"Trazado 1","mn":"ADBE Vector Shape - Group","hd":false},{"ty":"st","c":{"a":0,"k":[0.5216,0,0,1],"ix":3},"o":{"a":0,"k":100,"ix":4},"w":{"a":0,"k":2.835,"ix":5},"lc":2,"lj":2,"bm":0,"nm":"Trazo 1","mn":"ADBE Vector Graphic - Stroke","hd":false},{"ty":"fl","c":{"a":0,"k":[1,0.8588,0.8588,1],"ix":4},"o":{"a":0,"k":100,"ix":5},"r":1,"bm":0,"nm":"Relleno 1","mn":"ADBE Vector Graphic - Fill","hd":false},{"ty":"tr","p":{"a":0,"k":[116.988,59.832],"ix":2},"a":{"a":0,"k":[0,0],"ix":1},"s":{"a":0,"k":[100,100],"ix":3},"r":{"a":0,"k":0,"ix":6},"o":{"a":0,"k":100,"ix":7},"sk":{"a":0,"k":0,"ix":4},"sa":{"a":0,"k":0,"ix":5},"nm":"Transformar"}],"nm":"Grupo 11","np":3,"cix":2,"bm":0,"ix":11,"mn":"ADBE Vector Group","hd":false},{"ty":"gr","it":[{"ind":0,"ty":"sh","ix":1,"ks":{"a":0,"k":{"i":[[0,6.171],[0,0],[12.548,-3.134],[0.64,-23.816],[0.01,0.152],[-14.164,3.536]],"o":[[0,0],[0,6.171],[-13.383,3.341],[0,0],[-1.975,-29.026],[12.548,-3.134]],"v":[[27.662,-26.192],[27.662,-9.924],[8.726,4.988],[-25.785,26.192],[-25.686,14.414],[8.726,-11.28]],"c":true},"ix":2},"nm":"Trazado 1","mn":"ADBE Vector Shape - Group","hd":false},{"ty":"st","c":{"a":0,"k":[0.5216,0,0,1],"ix":3},"o":{"a":0,"k":100,"ix":4},"w":{"a":0,"k":2.835,"ix":5},"lc":2,"lj":2,"bm":0,"nm":"Trazo 1","mn":"ADBE Vector Graphic - Stroke","hd":false},{"ty":"fl","c":{"a":0,"k":[0.424,0.376,0.376,1],"ix":4},"o":{"a":0,"k":100,"ix":5},"r":1,"bm":0,"nm":"Relleno 1","mn":"ADBE Vector Graphic - Fill","hd":false},{"ty":"tr","p":{"a":0,"k":[134.335,68.905],"ix":2},"a":{"a":0,"k":[0,0],"ix":1},"s":{"a":0,"k":[100,100],"ix":3},"r":{"a":0,"k":0,"ix":6},"o":{"a":0,"k":100,"ix":7},"sk":{"a":0,"k":0,"ix":4},"sa":{"a":0,"k":0,"ix":5},"nm":"Transformar"}],"nm":"Grupo 12","np":3,"cix":2,"bm":0,"ix":12,"mn":"ADBE Vector Group","hd":false},{"ty":"gr","it":[{"ind":0,"ty":"sh","ix":1,"ks":{"a":0,"k":{"i":[[-3.351,-1.323],[0,-1.356],[1.724,-1.454],[3.351,1.334],[0,1.344],[0,0],[-1.725,1.442]],"o":[[1.659,0.662],[0,1.377],[-3.406,2.852],[-1.659,-0.661],[0,0],[0,-1.388],[3.405,-2.853]],"v":[[6.171,-5.178],[8.655,-2.001],[6.063,2.414],[-6.171,5.167],[-8.655,2.001],[-8.655,1.991],[-6.062,-2.412]],"c":true},"ix":2},"nm":"Trazado 1","mn":"ADBE Vector Shape - Group","hd":false},{"ty":"st","c":{"a":0,"k":[0.5216,0,0,1],"ix":3},"o":{"a":0,"k":100,"ix":4},"w":{"a":0,"k":2.835,"ix":5},"lc":2,"lj":2,"bm":0,"nm":"Trazo 1","mn":"ADBE Vector Graphic - Stroke","hd":false},{"ty":"fl","c":{"a":0,"k":[1,0.8588,0.8588,1],"ix":4},"o":{"a":0,"k":100,"ix":5},"r":1,"bm":0,"nm":"Relleno 1","mn":"ADBE Vector Graphic - Fill","hd":false},{"ty":"tr","p":{"a":0,"k":[160.358,19.693],"ix":2},"a":{"a":0,"k":[0,0],"ix":1},"s":{"a":0,"k":[100,100],"ix":3},"r":{"a":0,"k":0,"ix":6},"o":{"a":0,"k":100,"ix":7},"sk":{"a":0,"k":0,"ix":4},"sa":{"a":0,"k":0,"ix":5},"nm":"Transformar"}],"nm":"Grupo 13","np":3,"cix":2,"bm":0,"ix":13,"mn":"ADBE Vector Group","hd":false},{"ty":"gr","it":[{"ind":0,"ty":"sh","ix":1,"ks":{"a":0,"k":{"i":[[0,1.377],[0,0],[0,-2.429],[0,0],[0.488,-0.162],[1.562,1.909],[2.961,1.573],[0,0],[-1.659,-0.662],[-3.406,2.852]],"o":[[0,0],[-3.752,2.397],[0,0],[-0.466,0.217],[-0.38,-1.898],[-1.778,-2.169],[0,0],[0,1.345],[3.352,1.334],[1.724,-1.453]],"v":[[8.655,-11.599],[8.655,-5.211],[2.895,2.435],[2.895,11.035],[1.453,11.599],[-1.453,5.862],[-8.655,0.233],[-8.655,-7.597],[-6.171,-4.43],[6.063,-7.185]],"c":true},"ix":2},"nm":"Trazado 1","mn":"ADBE Vector Shape - Group","hd":false},{"ty":"st","c":{"a":0,"k":[0.5216,0,0,1],"ix":3},"o":{"a":0,"k":100,"ix":4},"w":{"a":0,"k":2.835,"ix":5},"lc":2,"lj":2,"bm":0,"nm":"Trazo 1","mn":"ADBE Vector Graphic - Stroke","hd":false},{"ty":"fl","c":{"a":0,"k":[0.424,0.376,0.376,1],"ix":4},"o":{"a":0,"k":100,"ix":5},"r":1,"bm":0,"nm":"Relleno 1","mn":"ADBE Vector Graphic - Fill","hd":false},{"ty":"tr","p":{"a":0,"k":[160.359,29.292],"ix":2},"a":{"a":0,"k":[0,0],"ix":1},"s":{"a":0,"k":[100,100],"ix":3},"r":{"a":0,"k":0,"ix":6},"o":{"a":0,"k":100,"ix":7},"sk":{"a":0,"k":0,"ix":4},"sa":{"a":0,"k":0,"ix":5},"nm":"Transformar"}],"nm":"Grupo 14","np":3,"cix":2,"bm":0,"ix":14,"mn":"ADBE Vector Group","hd":false},{"ty":"gr","it":[{"ind":0,"ty":"sh","ix":1,"ks":{"a":0,"k":{"i":[[-4.729,-2.744],[0,-1.584],[4.37,-2.516],[4.739,2.733],[0,1.583],[-3.768,2.373],[-0.337,0.195]],"o":[[1.779,1.03],[0,2.624],[-6.996,4.035],[-1.779,-1.031],[0,-2.429],[0.313,-0.197],[7.001,-4.053]],"v":[[12.668,-7.299],[15.302,-3.275],[8.568,4.956],[-12.678,7.31],[-15.302,3.286],[-9.544,-4.36],[-8.579,-4.946]],"c":true},"ix":2},"nm":"Trazado 1","mn":"ADBE Vector Shape - Group","hd":false},{"ty":"st","c":{"a":0,"k":[0.5216,0,0,1],"ix":3},"o":{"a":0,"k":100,"ix":4},"w":{"a":0,"k":2.835,"ix":5},"lc":2,"lj":2,"bm":0,"nm":"Trazo 1","mn":"ADBE Vector Graphic - Stroke","hd":false},{"ty":"fl","c":{"a":0,"k":[1,0.8588,0.8588,1],"ix":4},"o":{"a":0,"k":100,"ix":5},"r":1,"bm":0,"nm":"Relleno 1","mn":"ADBE Vector Graphic - Fill","hd":false},{"ty":"tr","p":{"a":0,"k":[178.557,28.441],"ix":2},"a":{"a":0,"k":[0,0],"ix":1},"s":{"a":0,"k":[100,100],"ix":3},"r":{"a":0,"k":0,"ix":6},"o":{"a":0,"k":100,"ix":7},"sk":{"a":0,"k":0,"ix":4},"sa":{"a":0,"k":0,"ix":5},"nm":"Transformar"}],"nm":"Grupo 15","np":3,"cix":2,"bm":0,"ix":15,"mn":"ADBE Vector Group","hd":false},{"ty":"gr","it":[{"ind":0,"ty":"sh","ix":1,"ks":{"a":0,"k":{"i":[[0,2.625],[0,0],[4.371,-2.516],[4.74,2.744],[0,1.584],[0,0],[-1.779,-1.03],[-6.995,4.034]],"o":[[0,0],[0,2.625],[-6.995,4.045],[-1.779,-1.019],[0,0],[0,1.584],[4.74,2.733],[4.371,-2.516]],"v":[[15.303,-14.799],[15.303,1.469],[8.567,9.702],[-12.679,12.055],[-15.303,8.031],[-15.303,-8.237],[-12.679,-4.213],[8.567,-6.566]],"c":true},"ix":2},"nm":"Trazado 1","mn":"ADBE Vector Shape - Group","hd":false},{"ty":"st","c":{"a":0,"k":[0.5216,0,0,1],"ix":3},"o":{"a":0,"k":100,"ix":4},"w":{"a":0,"k":2.835,"ix":5},"lc":2,"lj":2,"bm":0,"nm":"Trazo 1","mn":"ADBE Vector Graphic - Stroke","hd":false},{"ty":"fl","c":{"a":0,"k":[0.424,0.376,0.376,1],"ix":4},"o":{"a":0,"k":100,"ix":5},"r":1,"bm":0,"nm":"Relleno 1","mn":"ADBE Vector Graphic - Fill","hd":false},{"ty":"tr","p":{"a":0,"k":[178.557,39.964],"ix":2},"a":{"a":0,"k":[0,0],"ix":1},"s":{"a":0,"k":[100,100],"ix":3},"r":{"a":0,"k":0,"ix":6},"o":{"a":0,"k":100,"ix":7},"sk":{"a":0,"k":0,"ix":4},"sa":{"a":0,"k":0,"ix":5},"nm":"Transformar"}],"nm":"Grupo 16","np":3,"cix":2,"bm":0,"ix":16,"mn":"ADBE Vector Group","hd":false},{"ty":"gr","it":[{"ind":0,"ty":"sh","ix":1,"ks":{"a":0,"k":{"i":[[-0.011,-1.345],[0,0],[1.107,-0.825],[0,0],[3.395,1.529],[0,0],[0,1.345],[-1.107,0.824],[0,0],[-3.406,-1.53],[0,0]],"o":[[0,0],[0,0.965],[0,0],[-2.646,1.963],[0,0],[-1.974,-0.89],[0,-0.965],[0,0],[2.646,-1.963],[0,0],[1.984,0.889]],"v":[[112.846,-17.661],[112.846,-17.65],[111.208,-14.896],[2.028,66.152],[-8.926,66.944],[-109.831,21.22],[-112.846,17.662],[-111.197,14.897],[-2.017,-66.152],[8.937,-66.942],[109.831,-21.218]],"c":true},"ix":2},"nm":"Trazado 1","mn":"ADBE Vector Shape - Group","hd":false},{"ty":"st","c":{"a":0,"k":[0.5216,0,0,1],"ix":3},"o":{"a":0,"k":100,"ix":4},"w":{"a":0,"k":2.835,"ix":5},"lc":2,"lj":2,"bm":0,"nm":"Trazo 1","mn":"ADBE Vector Graphic - Stroke","hd":false},{"ty":"fl","c":{"a":0,"k":[1,1,1,1],"ix":4},"o":{"a":0,"k":100,"ix":5},"r":1,"bm":0,"nm":"Relleno 1","mn":"ADBE Vector Graphic - Fill","hd":false},{"ty":"tr","p":{"a":0,"k":[115.263,70.309],"ix":2},"a":{"a":0,"k":[0,0],"ix":1},"s":{"a":0,"k":[100,100],"ix":3},"r":{"a":0,"k":0,"ix":6},"o":{"a":0,"k":100,"ix":7},"sk":{"a":0,"k":0,"ix":4},"sa":{"a":0,"k":0,"ix":5},"nm":"Transformar"}],"nm":"Grupo 17","np":3,"cix":2,"bm":0,"ix":17,"mn":"ADBE Vector Group","hd":false},{"ty":"gr","it":[{"ind":0,"ty":"sh","ix":1,"ks":{"a":0,"k":{"i":[[0,0.965],[0,0],[1.107,-0.824],[0,0],[3.395,1.529],[0,0],[0,1.334],[0,0],[-1.974,-0.89],[0,0],[-2.646,1.963],[0,0]],"o":[[0,0],[0,0.976],[0,0],[-2.646,1.963],[0,0],[-1.974,-0.889],[0,0],[0,1.344],[0,0],[3.395,1.529],[0,0],[1.107,-0.824]],"v":[[112.846,-47.4],[112.846,-38.733],[111.208,-35.969],[2.028,45.079],[-8.926,45.871],[-109.831,0.147],[-112.846,-3.41],[-112.846,-12.086],[-109.831,-8.529],[-8.926,37.195],[2.028,36.403],[111.208,-44.645]],"c":true},"ix":2},"nm":"Trazado 1","mn":"ADBE Vector Shape - Group","hd":false},{"ty":"st","c":{"a":0,"k":[0.5216,0,0,1],"ix":3},"o":{"a":0,"k":100,"ix":4},"w":{"a":0,"k":2.835,"ix":5},"lc":2,"lj":2,"bm":0,"nm":"Trazo 1","mn":"ADBE Vector Graphic - Stroke","hd":false},{"ty":"fl","c":{"a":0,"k":[0.5216,0,0,1],"ix":4},"o":{"a":0,"k":100,"ix":5},"r":1,"bm":0,"nm":"Relleno 1","mn":"ADBE Vector Graphic - Fill","hd":false},{"ty":"tr","p":{"a":0,"k":[115.263,100.058],"ix":2},"a":{"a":0,"k":[0,0],"ix":1},"s":{"a":0,"k":[100,100],"ix":3},"r":{"a":0,"k":0,"ix":6},"o":{"a":0,"k":100,"ix":7},"sk":{"a":0,"k":0,"ix":4},"sa":{"a":0,"k":0,"ix":5},"nm":"Transformar"}],"nm":"Grupo 18","np":3,"cix":2,"bm":0,"ix":18,"mn":"ADBE Vector Group","hd":false}],"ip":0,"op":180.00000733155,"st":0,"bm":0}],"markers":[]}